untrusted_processes/__init__.py
untrusted_processes/core.py
untrusted_processes/setup.py
untrusted_processes-0.1.dist-info/METADATA
untrusted_processes-0.1.dist-info/WHEEL
untrusted_processes-0.1.dist-info/top_level.txt
untrusted_processes-0.1.dist-info/RECORD
