Metadata-Version: 2.1
Name: untrusted-processes
Version: 0.1
Requires-Dist: pandas
Requires-Dist: matplotlib
